{
  "pokemon": [{
    "id": 1,
    "num": "001",
    "name": "ราศีเมษ",
    "img": "https://raw.githubusercontent.com/chadaporn29797/tiktry/3cd17c97080e16744982b23cc363d6036959f145/capricorn.png",
    "type": [
      "สีแดงเลือด"
    ],
    "height": "13 ม.ษ. - 13 พ.ค.",
    "weight": "ราศีเมษมีดาวประจำราศีคือ ดาวอังคาร หรือ Mars ถูกตั้งชื่อตามเทพเจ้าแห่งสงครามของโรมัน ซึ่งมีนิสัยห้าวหาญ ไม่กลัวใคร อันเป็นลักษณะนิสัยที่พบในคนที่เกิดราศีนี้ด้วย ดาวประจำราศีนี้ทำให้คนที่เกิดราศีเมษเป็นคนมีพละกำลัง แข็งแรง ร่าเริง และอดทน มุ่งตรงไปยังเป้าหมาย โดยไม่มัวแต่พิรี้พิไรให้เสียการ",
    "candy": "Bulbasaur Candy",
    "candy_count": 25,
    "egg": "2 km",
    "spawn_chance": 0.69,
    "avg_spawns": 69,
    "spawn_time": "20:00",
    "multipliers": [1.58],
    "weaknesses": [
      "ต้นฮอลลี่",
      "สับปะรด",
      "เสือ",
      "ฉลาม"
    ],
    "next_evolution": [{
      "num": "001",
      "name": "ดาวอังคาร"
    }]
  }, {
    "id": 2,
    "num": "002",
    "name": "ราศีพฤษภ",
    "img": "https://raw.githubusercontent.com/chadaporn29797/tiktry/3cd17c97080e16744982b23cc363d6036959f145/taurus.png",
    "type": [
      "สีชมพู","สีฟ้า"
    ],
    "height": "15 พ.ค. - 14 มิ.ย.",
      "weight": "ราศีพฤษภหรือราศีวัว เป็นดาวที่อยู่ใต้อิทธิพลของดาวศุกร์ (Venus) เช่นเดียวกับผู้ที่อยู่ในราศีตุลย์ ถูกตั้งชื่อตามเทพธิดาแห่งความงามและความรักของโรมัน ซึ่งเชื่อว่าจะนำอิทธิพลที่ดีมาสู่ชีวิต ผู้ที่เกิดภายใต้ราศีนี้ โดยมากเป็นคนอ่อนโยน ขี้สงสาร และมีความสุขโดยธรรมชาติ ร่วมไปกับคุณสมบัติอื่นๆ ที่ติดตัวมาแต่กำเนิด ไม่ว่าจะเป็นคนชอบสร้างมิตร ฉลาดเฉลียว มีพรสวรรค์ด้านดนตรีและบันเทิง",
    "candy": "Bulbasaur Candy",
    "candy_count": 25,
    "egg": "2 km",
    "spawn_chance": 0.69,
    "avg_spawns": 69,
    "spawn_time": "20:00",
    "multipliers": [1.58],
    "weaknesses": [
      "ดอกเดซี",
      "หงส์",
      "ปลาแซลมอน",
      "นกพิราบ"
    ],
    "next_evolution": [{
      "num": "002",
      "name": "ดาวศุกร์"
    }]
  },{
    "id": 3,
    "num": "003",
    "name": "ราศีเมถุน",
    "img": "https://raw.githubusercontent.com/chadaporn29797/tiktry/3cd17c97080e16744982b23cc363d6036959f145/gemini.png",
    "type": [
     "สีเหลืองอมส้ม","สีท้องฟ้า"
    ],
    "height": "15 มิ.ย. - 16 ก.ค.",
    "weight": "ราศีเมถุนหรือราศีคนคู่เป็นดาวที่อยู่ใต้อิทธิพลของดาวพุธหรือเมอร์คิวรี ซึ่งเป็นเทพแห่งการสื่อสาร มีของวิเศษเป็นรองเท้าและหมวกมีปีก ซึ่งถือเป็นตัวแทนของอุปนิสัยที่รู้จักปรับตัวและยืดหยุ่น ผู้ที่อยู่ในราศีนี้จึงรู้จักวิธีรับมือกับสถานการณ์ทุกประเภท แม้บางทีจะดูเหมือนโชคชะตาเล่นตลกแต่คนกลุ่มนี้ก็ยังรู้จักปรับตัวให้เข้ากับสิ่งรอบข้าง หรือแม้กระทั่งปรับความคิดและหลักจริยธรรมให้สอดคล้องกับโลกที่เปลี่ยนแปลงได้",
    "candy": "Bulbasaur Candy",
    "candy_count": 25,
    "egg": "2 km",
    "spawn_chance": 0.69,
    "avg_spawns": 69,
    "spawn_time": "20:00",
    "multipliers": [1.58],
    "weaknesses": [
      "ดอกลิลลี่",
      "ลิง",
      "แครอท",
      "บุษราคัม"
    ],
    "next_evolution": [{
      "num": "003",
      "name": "ดาวพุธ"
    }]
  },{
    "id": 4,
    "num": "004",
    "name": "ราศีกรกฎ",
    "img": "https://raw.githubusercontent.com/chadaporn29797/tiktry/3cd17c97080e16744982b23cc363d6036959f145/zodiac.png",
    "type": [
      "สีเขียว","สีเทาเงิน","สีขาว"
    ],
    "height": "17 ก.ค. - 16 ส.ค.",
    "weight": "ราศีกรกฎหรือดาวปู เป็นดาวที่อยู่ใต้อิทธิพลของดวงจันทร์ ซึ่งตามหลักดาราศาสตร์แล้วไม่ใช่ดาวเคราะห์ นักโหราศาสตร์เองก็มองเช่นเดียวกัน อิทธิพลจากดวงจันทร์ส่งผลให้คนราศีกรกฎเป็นคนค่อนข้างอ่อนไหวง่าย แต่อย่างไรก็ดียังอยู่ในขอบเขตที่เข้าใจและควบคุมได้ ผู้ที่อยู่ในราศีนี้เป็นคนมีจินตนาการสดใสและแจ่มชัดมาก",
    "candy": "Bulbasaur Candy",
    "candy_count": 25,
    "egg": "2 km",
    "spawn_chance": 0.69,
    "avg_spawns": 69,
    "spawn_time": "20:00",
    "multipliers": [1.58],
    "weaknesses": [
      "ต้นหลิว",
      "เมลอน",
      "ผักกาดหอม",
      "ไข่มุก"
    ],
    "next_evolution": [{
      "num": "004",
      "name": "ดวงจันทร์"
    }]
  },{
    "id": 5,
    "num": "005",
    "name": "ราศีสิงห์",
    "img": "https://raw.githubusercontent.com/chadaporn29797/tiktry/3cd17c97080e16744982b23cc363d6036959f145/leo.png",
    "type": [
      "สีทอง","สีส้ม","สีเหลือง"
    ],
    "height": "17 ส.ค. - 16 ก.ย.",
    "weight": "ราศีสิงห์ที่ร้อนแรงเป็นราศีที่อยู่ใต้อิทธิพลของดวงอาทิตย์ ซึ่งในทางดาราศาสตร์เป็นดาวฤกษ์ไม่ใช่ดาวเคราะห์ แต่ในทางโหราศาสตร์ก็ยังถือเป็นดวงดาว จึงถูกนับเป็นหนึ่งในจักรราศีอันเป็นสัญลักษณ์ของราศีสิงห์ ตามความเชื่อของโรมัน เทพแห่งดวงอาทิตย์ คือ อพอลโล คนที่เกิดในราศีนี้ จึงถือได้ว่าดวงอาทิตย์ได้มอบพลังงาน ความสนุกสนาน",
    "candy": "Bulbasaur Candy",
    "candy_count": 25,
    "egg": "2 km",
    "spawn_chance": 0.69,
    "avg_spawns": 69,
    "spawn_time": "20:00",
    "multipliers": [1.58],
    "weaknesses": [
      "ดอกดาวเรือง",
      "ต้นปาล์ม",
      "องุ่น",
      "สิงโต"
    ],
    "next_evolution": [{
      "num": "005",
      "name": "ดวงอาทิตย์"
    }]
  },{
    "id": 6,
    "num": "006",
    "name": "ราศีกันย์",
    "img": "https://raw.githubusercontent.com/chadaporn29797/tiktry/3cd17c97080e16744982b23cc363d6036959f145/virgo.png",
    "type": [
      "สีเหลือง","สีของท้องฟ้า"
    ],
    "height": "17 ก.ย. - 17 ต.ค.",
    "weight": "ราศีกันย์อยู่ใต้อิทธิพลของดาวพุธหรือเมอร์คิวรี (Mercury)  เช่นเดียวกับผู้ที่อยู่ในราศีเมถุน เมอร์คิวรีเป็นเทพแห่งการสื่อสารตามตำนานของชาวโรมัน มีของวิเศษเป็นรองเท้าและหมวกมีปีก ถือเป็นตัวแทนของอุปนิสัยที่รู้จักปรับตัว ยืดหยุ่น และใช้สิ่งที่มีอยู่ให้เกิดประโยชน์ บุคลิกของผู้ที่เกิดภายใต้ราศีนี้ เป็นคนที่ทำตามแนวคิดและศีลธรรมตามแบบที่สอดคล้องกับสังคมในยุคสมัยนั้นๆ",
    "candy": "Bulbasaur Candy",
    "candy_count": 25,
    "egg": "2 km",
    "spawn_chance": 0.69,
    "avg_spawns": 69,
    "spawn_time": "20:00",
    "multipliers": [1.58],
    "weaknesses": [
      "ดอกลิลลี่",
      "วอลนัท",
      "นกแก้ว",
      "หินโมรา"
    ],
    "next_evolution": [{
      "num": "006",
      "name": "ดาวพุธ"
    }]
  },{
    "id": 7,
    "num": "007",
    "name": "ราศีตุลย์",
    "img": "https://raw.githubusercontent.com/chadaporn29797/tiktry/3cd17c97080e16744982b23cc363d6036959f145/libra.png",
    "type": [
      "สีชมพูโทนพาสเทล","สีฟ้า"  
    ],
    "height": "18 ต.ค. - 16 พ.ย.",
    "weight": "ราศีตุลย์ ซึ่งอยู่ภายใต้อิทธิพลของวีนัสหรือดาวศุกร์ กลุ่มดาวแห่งความงาม เช่นเดียวกับผู้ที่เกิดในราศีพฤษภ ในตำนานของชาวโรมัน วีนัสถือเป็นเทพธิดาแห่งความรักและความงาม ชาวราศีตุลย์เป็นคนสอดคล้องกับธรรมชาติ ชอบแสวงหาความสุขและมิตรภาพ เป็นคนงดงาม มีเสน่ห์ รักเสียงเพลง และชอบความเบิกบานใจ",
    "candy": "Bulbasaur Candy",
    "candy_count": 25,
    "egg": "2 km",
    "spawn_chance": 0.69,
    "avg_spawns": 69,
    "spawn_time": "20:00",
    "multipliers": [1.58],
    "weaknesses": [
      "ดอกแดฟโฟดิล",
      "โลมา",
      "หงส์",
      "คาร์เนเลียน"
    ],
    "next_evolution": [{
      "num": "007",
      "name": "ดาวศุกร์"
    }]
  },{
    "id": 8,
    "num": "008",
    "name": "ราศีพิจิก",
    "img": "https://raw.githubusercontent.com/chadaporn29797/tiktry/3cd17c97080e16744982b23cc363d6036959f145/scorpio.png",
    "type": [
      "สีดำ","สีน้ำตาลแดง","สีเทาถ่าน"
    ],
    "height": "17 พ.ย. - 15 ธ.ค.",
    "weight": "คนราศีพิจิกมีทั้งอำนาจความสำเร็จเฉพาะบุคคลและต้องการความร่วมมือและแบ่งปันกับผู้อื่น นอกจากนี้ดาวพลูโตยังมีส่วนเกี่ยวข้องอย่างแน่นแฟ้นกับอำนาจ รวมถึงยังมีความเชื่อว่า ดาวที่ส่งผลต่อราศีพิจิกนอกจากจะมีดาวพลูโตแล้ว ยังมีดาวอังคารด้วย ส่งผลให้คนที่เกิดในราศีนี้มีคุณลักษณะที่เด่นชัดในด้านพรสวรรค์ เสน่ห์อันลึกลับ ความน่าเชื่อถือ ความอดทน ความอยากรู้อยากเห็น ช่างสงสัย ยืดหยุ่น แต่ในทางลบก็อาจส่งผลในทางทำลายตัวเองได้ คนราศีนี้ต้องการเป็นผู้ควบคุมทุกสิ่ง โดยเฉพาะเรื่องความรัก",
    "candy": "Bulbasaur Candy",
    "candy_count": 25,
    "egg": "2 km",
    "spawn_chance": 0.69,
    "avg_spawns": 69,
    "spawn_time": "20:00",
    "multipliers": [1.58],
    "weaknesses": [
      "กระเทียม",
      "หัวหอม",
      "ผักกินรากที่มีรสจัด"
    ],
    "next_evolution": [{
      "num": "008",
      "name": "ดาวพลูโต"
    }, {
      "num": "008",
      "name": "ดาวอังคาร"
    }]
  },{
    "id": 9,
    "num": "009",
    "name": "ราศีธนู",
    "img": "https://raw.githubusercontent.com/chadaporn29797/tiktry/3cd17c97080e16744982b23cc363d6036959f145/sagittarius.png",
    "type": [
     "สีบรอนซ์","สีฟ้าเดนิม"," สีคราม","สีแดง"
    ],
    "height": "16 ธ.ค. - 14 ม.ค.",
    "weight": "คนที่เกิดในราศีธนู ได้รับอิทธิพลจากดาวพฤหัส ได้รับพรด้านการเจริญเติบโต ความก้าวหน้า ความมั่งคั่ง และโชคเป็นอย่างมาก มีอุปนิสัยที่โดดเด่นในด้านคุณธรรม จริยธรรมสูง มีความเมตตา ความร่าเริง รวมถึงเป็นนักอุดมคติด้วย คนในราศีนี้มีแนวโน้มให้ความสำคัญกับอิสรภาพ และมีแรงปรารถนาในการสำรวจและค้นพบ เชื่อมโยงไปจนถึงเรื่องที่ต้องเกี่ยวข้องกับต่างประเทศ ไม่ว่าจะเป็นการเดินทาง การศึกษา ศาสนา และกฎหมาย",
    "candy": "Bulbasaur Candy",
    "candy_count": 25,
    "egg": "2 km",
    "spawn_chance": 0.69,
    "avg_spawns": 69,
    "spawn_time": "20:00",
    "multipliers": [1.58],
    "weaknesses": [
      "หน่อไม้ฝรั่ง",
      "ผลไม้แห้ง",
      "เกาลัด",
      "ถั่วเหลือง"
    ],
    "next_evolution": [{
      "num": "009",
      "name": "ดาวพฤหัส"
    }]
  },{
    "id": 10,
    "num": "010",
    "name": "ราศีมังกร",
    "img": "https://raw.githubusercontent.com/chadaporn29797/tiktry/3cd17c97080e16744982b23cc363d6036959f145/aries.png",
    "type": [
      "สีดำ","สีเอิร์ธโทน",
      "สีส้ม"
    ],
    "height": "15 ม.ค. - 12 ก.พ.",
    "weight": "เป็นคนขี้กังวลเกี่ยวกับอนาคตและการวางแผนในระยะยาว ในด้านระบบร่างกาย ดาวเสาร์เชื่อมโยงกับโครงสร้างด้านโครงกระดูก ผิวหนัง ฟัน ถุงน้ำดี ม้าม และเส้นประสาทเวกัส ในช่วงเวลาก่อนการค้นพบดาวยูเรนัสในสุริยจักรวาลนั้น ดาวเสาร์นอกจากจะเป็นดาวประจำราศีมังกรแล้ว ยังเป็นดาวประจำราศีกุมภ์ด้วย ซึ่งนักโหราศาสตร์ส่วนใหญ่ก็ยังเชื่อเช่นนั้นมาจนถึงทุกวันนี้",
    "candy": "Bulbasaur Candy",
    "candy_count": 25,
    "egg": "2 km",
    "spawn_chance": 0.69,
    "avg_spawns": 69,
    "spawn_time": "20:00",
    "multipliers": [1.58],
    "weaknesses": [
      "ต้นเอลเดอร์",
      "ดอกเบอร์ดอค",
      "ต้นยู",
      "ต้นวีปปิงวิลโลว์"
    ],
    "next_evolution": [{
      "num": "010",
      "name": "ดาวเสาร์"
    }]
  },{
    "id": 11,
    "num": "011",
    "name": "ราศีกุมภ์",
    "img": "https://raw.githubusercontent.com/chadaporn29797/tiktry/3cd17c97080e16744982b23cc363d6036959f145/aquarius.png",
    "type": [
       "สีฟ้าน้ำเงิน"
    ],
    "height": "14 ก.พ. - 14 มี.ค.",
    "weight": "ราศีกุมภ์เป็นราศีที่อยู่ภายใต้อิทธิพลของดาวยูเรนัส ตัวแทนแห่งสวรรค์และท้องฟ้ายามราตรี ตามความเชื่อของเทพปกรณัมกรีก ดาวที่เป็นตัวแทนแห่งราศีกุมภ์นี้ มีความโดดเด่นแตกต่าง เนื่องจากมีการหมุนไปในทิศทางตรงกันข้ามกับดาวเคราะห์ดวงอื่น นั่นคือหมุนตามเข็มนาฬิกา และด้วยระนาบการวางตัวกับระบบสุริยะ",
    "candy": "Bulbasaur Candy",
    "candy_count": 25,
    "egg": "2 km",
    "spawn_chance": 0.69,
    "avg_spawns": 69,
    "spawn_time": "20:00",
    "multipliers": [1.58],
    "weaknesses": [
      "มะเดื่อ",
      "แอปเปิล",
      "มะนาว",
      "ดอกพีช"
    ],
    "next_evolution": [{
      "num": "011",
      "name": "ดาวยูเรนัส"
    },{
      "num": "011",
      "name": "ดาวเสาร์"
    }]
  },{
    "id": 12,
    "num": "012",
    "name": "ราศีมีน",
    "img": "https://raw.githubusercontent.com/chadaporn29797/tiktry/3cd17c97080e16744982b23cc363d6036959f145/zodiac%20(1).png",
    "type": [
      "สีเงิน",
      "สีเขียวน้ำทะเล"
    ],
    "height": "15 ม.ค. - 12 ก.พ.",
    "weight": "สัญลักษณ์ของราศีมีนคือรูปปลาสองตัว ว่ายวนในทิศทางตรงกันข้าม สะท้อนถึงความต้องการด้านหนึ่งของคุณที่อยากจะหนีออกจากโลกความเป็นจริง ขณะที่อีกด้านหนึ่งลางสังหรณ์อันว่องไวของคุณ ก็มักดึงคุณเข้าไปเกี่ยวข้องกับทุกอย่าง แต่ไม่ว่าคุณจะต้องการก้าวออกมาจากอะไรก็ตาม จินตนาการคือพื้นที่ลี้ภัยที่ดีที่สุดของคุณ คุณเป็นคนชอบเต้น",
    "candy": "Bulbasaur Candy",
    "candy_count": 25,
    "egg": "2 km",
    "spawn_chance": 0.69,
    "avg_spawns": 69,
    "spawn_time": "20:00",
    "multipliers": [1.58],
    "weaknesses": [
      "ดอกไอริส",
      "ดอกบัว",
      "เฟิร์น",
      "สาหร่ายทะเล"
    ],
    "next_evolution": [{
      "num": "012",
      "name": "ดาวเนปจูน"
    },{
      "num": "012",
      "name": "ดาวพฤหัส"
    }]
  }
]
}
